mount/__init__.py
mount/__main__.py
mount/cli.py
mount/core.py
mount/flags.py
mount-1.0.0.dist-info/LICENSE
mount-1.0.0.dist-info/METADATA
mount-1.0.0.dist-info/WHEEL
mount-1.0.0.dist-info/entry_points.txt
mount-1.0.0.dist-info/RECORD
