Metadata-Version: 2.1
Name: mount
Version: 1.0.0
Summary: Wrapper around sys/mount.h
Home-page: https://github.com/titaniumhocker/mount
License: MIT
Author: Ivan Fedorov
Author-email: inbox@titaniumhocker.ru
Requires-Python: >=3.9,<4.0
Classifier: Intended Audience :: Developers
Classifier: License :: OSI Approved :: MIT License
Classifier: Programming Language :: Python :: 3
Classifier: Programming Language :: Python :: 3.9
Classifier: Programming Language :: Python :: 3.10
Classifier: Programming Language :: Python :: 3.11
Classifier: Programming Language :: Python :: 3 :: Only
Classifier: Topic :: Software Development :: Libraries
Project-URL: Bug Tracker, https://github.com/titaniumhocker/mount/issues
Project-URL: Repository, https://github.com/titaniumhocker/mount
